.gitignore
AUTHORS
COPYING
Makefile
README
setup.cfg
setup.py
bin/kz
doc/conf.py
doc/epydoc.conf
doc/extapi.py
doc/index.rst
doc/kenozooid-logo.svg
doc/kenozooid.gaphor
doc/hacking/actors.rst
doc/hacking/drvarch.rst
doc/hacking/index.rst
doc/hacking/uc.rst
doc/hacking/us.rst
doc/homepage/docs.png
doc/homepage/fan.png
doc/homepage/index.html
doc/homepage/kenozooid.css
doc/homepage/penguin.png
doc/homepage/plot.png
doc/homepage/style.css
doc/lib/calc.rst
doc/lib/cmp.rst
doc/lib/index.rst
doc/lib/intro.rst
doc/lib/uddf.rst
doc/lib/unit.rst
doc/static/kenozooid.css
doc/user/ack.rst
doc/user/analysis.rst
doc/user/backup.rst
doc/user/calc.rst
doc/user/changelog.rst
doc/user/dc.rst
doc/user/deco.rst
doc/user/index.rst
doc/user/intro.rst
doc/user/links.rst
doc/user/logbook.rst
doc/user/plan.rst
doc/user/plot.rst
doc/user/qt.rst
doc/user/ri.rst
doc/user/simulation.rst
doc/user/ui.rst
dumps/README
dumps/ostc-dump-01.uddf
dumps/ostc-dump-02.uddf
dumps/ostc-dump-03.uddf
dumps/ostc-dump-04.uddf
dumps/ostc-dump-05.uddf
dumps/ostc-dump-06.uddf
dumps/ostc-dump-07.uddf
dumps/ostc-dump-08.uddf
dumps/ostc-dump-09.uddf
dumps/ostc-dump-10.uddf
dumps/ostc-dump-11.uddf
dumps/ostc-dump-12.uddf
dumps/ostc-dump-13.uddf
dumps/ostc-dump-14.uddf
dumps/ostc-dump-15.uddf
dumps/ostc-dump-16.uddf
dumps/ostc-dump-17.uddf
dumps/ostc-dump-18.uddf
dumps/ostc-dump-19.uddf
dumps/ostc-dump-20.uddf
dumps/ostc-dump-21.uddf
dumps/ostc-dump-22.uddf
dumps/ostc-dump-23.uddf
dumps/ostc-dump-24.uddf
dumps/ostc-dump-25.uddf
dumps/ostc-dump-26.uddf
dumps/ostc-dump-27.uddf
dumps/ostc-dump-28.uddf
dumps/ostc-dump-29.uddf
dumps/ostc-dump-30.uddf
dumps/ostc-dump-31.uddf
dumps/ostc-dump-32.uddf
dumps/ostc-dump-33.uddf
dumps/ostc-dump-34.uddf
dumps/ostc-dump-35.uddf
dumps/ostc-dump-36.uddf
dumps/ostc-dump-37.uddf
dumps/ostc-dump-38.uddf
dumps/ostc-dump-39.uddf
dumps/ostc-dump-40.uddf
dumps/ostc-dump-41.uddf
dumps/ostc-dump-42.uddf
dumps/ostc-dump-43.uddf
dumps/ostc-dump-44.uddf
dumps/ostc-dump-45.uddf
kenozooid.egg-info/PKG-INFO
kenozooid.egg-info/SOURCES.txt
kenozooid.egg-info/dependency_links.txt
kenozooid.egg-info/requires.txt
kenozooid.egg-info/top_level.txt
