Metadata-Version: 1.1
Name: kenozooid
Version: 0.20.0
Summary: Kenozooid is dive planning and analysis toolbox
Home-page: https://wrobell.dcmod.org/kenozooid
Author: Artur Wroblewski
Author-email: wrobell@riseup.net
License: GPL
Keywords: diving dive computer logger plot dump uddf analytics
Platform: UNKNOWN
Classifier: License :: OSI Approved :: GNU General Public License (GPL)
Classifier: Programming Language :: Python
Classifier: Development Status :: 3 - Alpha
Classifier: Intended Audience :: End Users/Desktop
Classifier: Intended Audience :: Information Technology
Classifier: Intended Audience :: Science/Research
Classifier: Topic :: Scientific/Engineering
